memprocfs/dbghelp.dll
memprocfs/info.db
memprocfs/LICENSE.txt
memprocfs/license_dbghelp.txt
memprocfs/license_info_all.txt
memprocfs/license_lz4.txt
memprocfs/license_vmmyara.txt
memprocfs/memprocfs.py
memprocfs/plugins/m_vmemd.dll
memprocfs/plugins/pyp_reg_root_reg$net_bth$devices.py
memprocfs/plugins/pyp_reg_root_reg$net_tcpip$interfaces.py
memprocfs/plugins/pyp_reg_root_reg$usb_usb$devices.py
memprocfs/plugins/pyp_reg_root_reg$usb_usb$storage.py
memprocfs/plugins/pyp_reg_user_reg$user_wallpaper.py
memprocfs/redist_dbghelp.txt
memprocfs/redist_vcruntime.txt
memprocfs/Symbols/pingme.txt
memprocfs/symsrv.dll
memprocfs/vcruntime140.dll
memprocfs/vmm.dll
memprocfs/vmmpyc.pyd
memprocfs/vmmpyplugin.py
memprocfs/vmmyara.dll
memprocfs/__init__.py
memprocfs-5.16.12.dist-info/LICENSE
memprocfs-5.16.12.dist-info/METADATA
memprocfs-5.16.12.dist-info/top_level.txt
memprocfs-5.16.12.dist-info/WHEEL
memprocfs-5.16.12.dist-info/RECORD
