Metadata-Version: 2.1
Name: memprocfs
Version: 5.16.12
Summary: MemProcFS for Python
Home-page: https://github.com/ufrisk/MemProcFS
Author: Ulf Frisk
Author-email: pcileech@frizk.net
License: Other/Proprietary License
Platform: win_amd64
Classifier: Programming Language :: C
Classifier: Programming Language :: Python :: 3
Classifier: License :: Other/Proprietary License
Classifier: Operating System :: Microsoft :: Windows :: Windows 10
Requires-Python: >=3.6
Requires-Dist: leechcorepyc (>=2.22.0)
